unicorn_binance_websocket_api/__init__.c
unicorn_binance_websocket_api/__init__.cp313-win_amd64.pyd
unicorn_binance_websocket_api/__init__.py
unicorn_binance_websocket_api/__init__.pyi
unicorn_binance_websocket_api/connection.c
unicorn_binance_websocket_api/connection.cp313-win_amd64.pyd
unicorn_binance_websocket_api/connection.py
unicorn_binance_websocket_api/connection.pyi
unicorn_binance_websocket_api/connection_settings.c
unicorn_binance_websocket_api/connection_settings.cp313-win_amd64.pyd
unicorn_binance_websocket_api/connection_settings.py
unicorn_binance_websocket_api/connection_settings.pyi
unicorn_binance_websocket_api/exceptions.c
unicorn_binance_websocket_api/exceptions.cp313-win_amd64.pyd
unicorn_binance_websocket_api/exceptions.py
unicorn_binance_websocket_api/exceptions.pyi
unicorn_binance_websocket_api/manager.c
unicorn_binance_websocket_api/manager.cp313-win_amd64.pyd
unicorn_binance_websocket_api/manager.py
unicorn_binance_websocket_api/manager.pyi
unicorn_binance_websocket_api/restclient.c
unicorn_binance_websocket_api/restclient.cp313-win_amd64.pyd
unicorn_binance_websocket_api/restclient.py
unicorn_binance_websocket_api/restclient.pyi
unicorn_binance_websocket_api/restserver.c
unicorn_binance_websocket_api/restserver.cp313-win_amd64.pyd
unicorn_binance_websocket_api/restserver.py
unicorn_binance_websocket_api/restserver.pyi
unicorn_binance_websocket_api/sockets.c
unicorn_binance_websocket_api/sockets.cp313-win_amd64.pyd
unicorn_binance_websocket_api/sockets.py
unicorn_binance_websocket_api/sockets.pyi
unicorn_binance_websocket_api/api/__init__.c
unicorn_binance_websocket_api/api/__init__.cp313-win_amd64.pyd
unicorn_binance_websocket_api/api/api.c
unicorn_binance_websocket_api/api/api.cp313-win_amd64.pyd
unicorn_binance_websocket_api/api/futures.c
unicorn_binance_websocket_api/api/futures.cp313-win_amd64.pyd
unicorn_binance_websocket_api/api/spot.c
unicorn_binance_websocket_api/api/spot.cp313-win_amd64.pyd
unicorn_binance_websocket_api-2.10.2.dist-info/licenses/LICENSE
unicorn_binance_websocket_api-2.10.2.dist-info/METADATA
unicorn_binance_websocket_api-2.10.2.dist-info/WHEEL
unicorn_binance_websocket_api-2.10.2.dist-info/top_level.txt
unicorn_binance_websocket_api-2.10.2.dist-info/RECORD
