Metadata-Version: 2.4
Name: unicorn-binance-websocket-api
Version: 2.10.2
Summary: A Python SDK to use the Binance Websocket API`s (com+testnet, com-margin+testnet, com-isolated_margin+testnet, com-futures+testnet, com-coin_futures, us, tr, dex/chain+testnet) in a simple, fast, flexible, robust and fully-featured way.
Home-page: https://github.com/oliver-zehentleitner/unicorn-binance-websocket-api
Author: Oliver Zehentleitner
License: MIT
Project-URL: Howto, https://github.com/oliver-zehentleitner/unicorn-binance-websocket-api#howto
Project-URL: Documentation, https://oliver-zehentleitner.github.io/unicorn-binance-websocket-api
Project-URL: Wiki, https://github.com/oliver-zehentleitner/unicorn-binance-websocket-api/wiki
Project-URL: Author, https://www.linkedin.com/in/oliver-zehentleitner
Project-URL: Changes, https://oliver-zehentleitner.github.io/unicorn-binance-websocket-api/changelog.html
Project-URL: License, https://oliver-zehentleitner.github.io/unicorn-binance-websocket-api/license.html
Project-URL: Issue Tracker, https://github.com/oliver-zehentleitner/unicorn-binance-websocket-api/issues
Project-URL: Telegram, https://t.me/unicorndevs
Keywords: binance,asyncio,async,asynchronous,concurrent,websocket-api,webstream-api,binance-websocket,binance-webstream,webstream,websocket,api,binance-dex,binance-futures,binance-margin,binance-us
Classifier: Development Status :: 5 - Production/Stable
Classifier: Programming Language :: Python :: 3.8
Classifier: Programming Language :: Python :: 3.9
Classifier: Programming Language :: Python :: 3.10
Classifier: Programming Language :: Python :: 3.11
Classifier: Programming Language :: Python :: 3.12
Classifier: Programming Language :: Python :: 3.13
Classifier: Programming Language :: Cython
Classifier: Intended Audience :: Developers
Classifier: Intended Audience :: Financial and Insurance Industry
Classifier: Intended Audience :: Information Technology
Classifier: Intended Audience :: Science/Research
Classifier: Operating System :: OS Independent
Classifier: Topic :: Office/Business :: Financial :: Investment
Classifier: Topic :: Software Development :: Libraries :: Python Modules
Classifier: Framework :: AsyncIO
Requires-Python: >=3.8.0
License-File: LICENSE
Requires-Dist: colorama
Requires-Dist: requests>=2.31.0
Requires-Dist: websocket-client
Requires-Dist: websockets==11.0.3
Requires-Dist: flask_restful
Requires-Dist: cheroot
Requires-Dist: flask
Requires-Dist: orjson
Requires-Dist: psutil
Requires-Dist: PySocks
Requires-Dist: simplejson
Requires-Dist: unicorn-fy>=0.15.0
Requires-Dist: unicorn-binance-rest-api>=2.7.0
Requires-Dist: typing_extensions
Requires-Dist: Cython
Dynamic: author
Dynamic: classifier
Dynamic: description
Dynamic: description-content-type
Dynamic: home-page
Dynamic: keywords
Dynamic: license
Dynamic: license-file
Dynamic: project-url
Dynamic: requires-dist
Dynamic: requires-python
Dynamic: summary
